{"title":"The Mystery Of A Hansom Cab (2012)DVD5(NL subs)NLtoppers","uid":7801129,"size":4396236800,"categoryP":"video","categoryS":"movies_dvdr","magnet":"?xt=urn:btih:02229eeb6ce7f75325215220e259610343f8015c&amp;dn=The+Mystery+Of+A+Hansom+Cab+%282012%29DVD5%28NL+subs%29NLtoppers&amp;tr=udp%3A%2F%2Ftracker.openbittorrent.com%3A80&amp;tr=udp%3A%2F%2Fopen.demonii.com%3A1337&amp;tr=udp%3A%2F%2Ftracker.coppersurfer.tk%3A6969&amp;tr=udp%3A%2F%2Fexodus.desync.com%3A6969","seeders":0,"leechers":1,"uploader":"Yakomo","files":-1,"time":1352289495,"description":"The Mystery Of A Hansom Cab (2012)DVD5(NL subs)NLtoppers\n\n[img]http://img703.imageshack.us/img703/9176/themysteryofahansomcab.jpg[/img]\n\nOp basis van de internationale best-selling roman van Fergus Hume, Het mysterie van een Hansom Cab is nu een prachtig nieuw telefilm met onverwachte wendingen tot het einde. Melbourne, 1886. Twee heren klimmen laat in een duistere nacht in een hansom cabine . Een man stapt uit, de andere reizen naar St Kilda. Bij aankomst vind de bestuurder de tweede man dood; vermoord\n******************************************\nBased on the international best-selling novel by Fergus Hume,The Mystery of a Hansom Cab is now a stunning new telemovie with twists and turns to the very end. Melbourne, 1886. Two gentlemen climb into a hansom cab late one murky night. One man climbs out, the other travels on to St Kilda. On arrival, the driver finds the second man dead; murdered.The high-society killing sends shockwaves through the young city, still flush from its gold-rush boom. The victim, Oliver Whyte (Brett Climo), fresh from England with glowing letters of introduction, had endeared himself to one of the wealthiest men in the colony, Mark Frettlby (John Waters). It is Marks 21-year-old daughter, Madge Frettlby (Jessica De Gouw), who Whyte instantly sets his sights on, but Madge is already in love with Brian Fitzgerald (Oliver Ackland), a sensitive, hard-working Irishman.\n\n\nSource: The.Mystery.Of.A.Hansom.Cab.2012.PDTV.x264-W4F\nFormat: VIDEO_TS (DVD-5)\nBeeld: 720*576\nOndertitels: NEDERLANDS\nVertaling: Cranedriver &amp; SK\nControle: Smokey\n &lt;a href=&quot;\nhttp://www.imdb.com/title/tt2174072/&quot; rel=&quot;nofollow&quot; target=&quot;_NEW&quot;&gt;\nhttp://www.imdb.com/title/tt2174072/&lt;/a&gt;\n\n\nHeeft u deze film gezien en wilt u ergens een recensie achterlaten?\n\nGa dan eens naar http://www.pheunix.nl\n\nYakomo ","torrent":{"xt":"urn:btih:02229eeb6ce7f75325215220e259610343f8015c","amp;dn":"The+Mystery+Of+A+Hansom+Cab+%282012%29DVD5%28NL+subs%29NLtoppers","amp;tr":["udp%3A%2F%2Ftracker.openbittorrent.com%3A80","udp%3A%2F%2Fopen.demonii.com%3A1337","udp%3A%2F%2Ftracker.coppersurfer.tk%3A6969","udp%3A%2F%2Fexodus.desync.com%3A6969"],"infoHash":"02229eeb6ce7f75325215220e259610343f8015c","infoHashBuffer":{"type":"Buffer","data":[2,34,158,235,108,231,247,83,37,33,82,32,226,89,97,3,67,248,1,92]},"announce":[],"urlList":[]}}