{"title":"BBC Doctor Who The Best Of The Monsters xvid mp3 dvd rip","uid":7661387,"size":366486235,"categoryP":"video","categoryS":"tv_shows","magnet":"?xt=urn:btih:05611a3d75318c4217596d0b56b0c7e82bcef803&amp;dn=BBC+Doctor+Who+The+Best+Of+The+Monsters+xvid+mp3+dvd+rip&amp;tr=udp%3A%2F%2Ftracker.openbittorrent.com%3A80&amp;tr=udp%3A%2F%2Fopen.demonii.com%3A1337&amp;tr=udp%3A%2F%2Ftracker.coppersurfer.tk%3A6969&amp;tr=udp%3A%2F%2Fexodus.desync.com%3A6969","seeders":0,"leechers":4,"uploader":"catflap","files":2,"time":1348314456,"description":"Doctor Who - The Best Of The Monsters\n\nSize: 366,483,456 bytes (349.506 MB)\nPlay duration: 00:43:34\nXviD\nmp3\nDVD Rip\n\n**********\n**********\n\nThis is an extra from BBC America's\n2011 Christmas Special DVD &quot;The Doctor,\nThe Widow and The Wardrobe&quot;.\n\n**********\n**********\n\nTHIS IS MY OWN DVD RIP AND ENCODE.\n\nIF YOU WANT THE INFERIOR X264 VERSION, GO SOMEWHERE ELSE.\n\nDON'T COMPLAIN. DON'T WHINGE OR WHINE. IT'S FREE.\n\nAND I'M NOT INTERESTED.","torrent":{"xt":"urn:btih:05611a3d75318c4217596d0b56b0c7e82bcef803","amp;dn":"BBC+Doctor+Who+The+Best+Of+The+Monsters+xvid+mp3+dvd+rip","amp;tr":["udp%3A%2F%2Ftracker.openbittorrent.com%3A80","udp%3A%2F%2Fopen.demonii.com%3A1337","udp%3A%2F%2Ftracker.coppersurfer.tk%3A6969","udp%3A%2F%2Fexodus.desync.com%3A6969"],"infoHash":"05611a3d75318c4217596d0b56b0c7e82bcef803","infoHashBuffer":{"type":"Buffer","data":[5,97,26,61,117,49,140,66,23,89,109,11,86,176,199,232,43,206,248,3]},"announce":[],"urlList":[]}}