{"title":"RealityGang - TeenHitchhikers -  Madison Monroe ","uid":7759122,"size":885770413,"categoryP":"porn","categoryS":"movie_clips","magnet":"?xt=urn:btih:23e9a4fb0230aacd72c8559be2f6a0ac9c7f67ea&amp;dn=RealityGang+-+TeenHitchhikers+-++Madison+Monroe+&amp;tr=udp%3A%2F%2Ftracker.openbittorrent.com%3A80&amp;tr=udp%3A%2F%2Fopen.demonii.com%3A1337&amp;tr=udp%3A%2F%2Ftracker.coppersurfer.tk%3A6969&amp;tr=udp%3A%2F%2Fexodus.desync.com%3A6969","seeders":0,"leechers":2,"uploader":"xuluhulu","files":1,"time":1351180907,"description":"THUMBSNAIL SCREENS:\n\n &lt;a href=&quot;\nhttp://www.imgnip.com/viewer.php?file=04799146358999751724.jpeg&quot; rel=&quot;nofollow&quot; target=&quot;_NEW&quot;&gt;\nhttp://www.imgnip.com/viewer.php?file=04799146358999751724.jpeg&lt;/a&gt;\n\n\n\nSEED &amp; ENJOY!!!","torrent":{"xt":"urn:btih:23e9a4fb0230aacd72c8559be2f6a0ac9c7f67ea","amp;dn":"RealityGang+-+TeenHitchhikers+-++Madison+Monroe+","amp;tr":["udp%3A%2F%2Ftracker.openbittorrent.com%3A80","udp%3A%2F%2Fopen.demonii.com%3A1337","udp%3A%2F%2Ftracker.coppersurfer.tk%3A6969","udp%3A%2F%2Fexodus.desync.com%3A6969"],"infoHash":"23e9a4fb0230aacd72c8559be2f6a0ac9c7f67ea","infoHashBuffer":{"type":"Buffer","data":[35,233,164,251,2,48,170,205,114,200,85,155,226,246,160,172,156,127,103,234]},"announce":[],"urlList":[]}}