{"title":"Ayami.Syunnka.ABS-163.Jav.Censored.DVDRip.XviD-MotTto","uid":7775575,"size":1474656256,"categoryP":"porn","categoryS":"movies","magnet":"?xt=urn:btih:2c1963df4cc895c6525fdec84fde5870d13ae809&amp;dn=Ayami.Syunnka.ABS-163.Jav.Censored.DVDRip.XviD-MotTto++&amp;tr=udp%3A%2F%2Ftracker.openbittorrent.com%3A80&amp;tr=udp%3A%2F%2Fopen.demonii.com%3A1337&amp;tr=udp%3A%2F%2Ftracker.coppersurfer.tk%3A6969&amp;tr=udp%3A%2F%2Fexodus.desync.com%3A6969","seeders":0,"leechers":1,"uploader":"R0thschild","files":4,"time":1351644524,"description":"Gallery:\n  &lt;a href=&quot;\nhttp://imagedomino.com/?g=813281&quot; rel=&quot;nofollow&quot; target=&quot;_NEW&quot;&gt;\nhttp://imagedomino.com/?g=813281&lt;/a&gt;\n\nDVD Date...: 10/22/2012        Release Date...: 10/30/2012\n\nSource.....: DVD5 NTSC(16:9)   Video Codec....: XviD\n\nAspect Ratio: 1.739 : 1        Resolution.....: 640 x 368\n\nFrame Rate..: 29.970 FPS       Video Bitrate..: 1346Kbps avg\n\nAudio Codec.: AC3              Audio Bitrate..: 192Kbps 2.0ch\n\nRun time....: 125 min          Size...........: 700MB x 2 (2x50x15MB\n\nGenre....: Adult Porn          Language....: Japanese\n\nStudio...: Prestige            Starring....: Ayami Syunnka\t","torrent":{"xt":"urn:btih:2c1963df4cc895c6525fdec84fde5870d13ae809","amp;dn":"Ayami.Syunnka.ABS-163.Jav.Censored.DVDRip.XviD-MotTto++","amp;tr":["udp%3A%2F%2Ftracker.openbittorrent.com%3A80","udp%3A%2F%2Fopen.demonii.com%3A1337","udp%3A%2F%2Ftracker.coppersurfer.tk%3A6969","udp%3A%2F%2Fexodus.desync.com%3A6969"],"infoHash":"2c1963df4cc895c6525fdec84fde5870d13ae809","infoHashBuffer":{"type":"Buffer","data":[44,25,99,223,76,200,149,198,82,95,222,200,79,222,88,112,209,58,232,9]},"announce":[],"urlList":[]}}