{"title":"The Bold and the Beautiful Nov 1  2012","uid":7785767,"size":165549400,"categoryP":"video","categoryS":"tv_shows","magnet":"?xt=urn:btih:3fcdee0c8b7eaf073da60d23cc88cdc6f51821e8&amp;dn=The+Bold+and+the+Beautiful+Nov+1++2012&amp;tr=udp%3A%2F%2Ftracker.openbittorrent.com%3A80&amp;tr=udp%3A%2F%2Fopen.demonii.com%3A1337&amp;tr=udp%3A%2F%2Ftracker.coppersurfer.tk%3A6969&amp;tr=udp%3A%2F%2Fexodus.desync.com%3A6969","seeders":0,"leechers":0,"uploader":"MsFenmore","files":1,"time":1351888632,"description":"Nov 1st 2012","torrent":{"xt":"urn:btih:3fcdee0c8b7eaf073da60d23cc88cdc6f51821e8","amp;dn":"The+Bold+and+the+Beautiful+Nov+1++2012","amp;tr":["udp%3A%2F%2Ftracker.openbittorrent.com%3A80","udp%3A%2F%2Fopen.demonii.com%3A1337","udp%3A%2F%2Ftracker.coppersurfer.tk%3A6969","udp%3A%2F%2Fexodus.desync.com%3A6969"],"infoHash":"3fcdee0c8b7eaf073da60d23cc88cdc6f51821e8","infoHashBuffer":{"type":"Buffer","data":[63,205,238,12,139,126,175,7,61,166,13,35,204,136,205,198,245,24,33,232]},"announce":[],"urlList":[]}}