{"title":"Sundara Pandiyan Tc DvD - 700Mb","uid":7649468,"size":747855564,"categoryP":"video","categoryS":"movies","magnet":"?xt=urn:btih:4312e2f2ae12f8ac133f811ace7d14bb16992628&amp;dn=Sundara+Pandiyan+Tc+DvD+-+700Mb&amp;tr=udp%3A%2F%2Ftracker.openbittorrent.com%3A80&amp;tr=udp%3A%2F%2Fopen.demonii.com%3A1337&amp;tr=udp%3A%2F%2Ftracker.coppersurfer.tk%3A6969&amp;tr=udp%3A%2F%2Fexodus.desync.com%3A6969","seeders":0,"leechers":1,"uploader":"crazylvs","files":1,"time":1347984264,"description":"Sundara Pandiyan Tc DvD - 700Mb\n\n\nDirect Download Links At : \n\n &lt;a href=&quot;\nhttp://tamillegends.com/sundara-pandiyan-tc-dvd/&quot; rel=&quot;nofollow&quot; target=&quot;_NEW&quot;&gt;\nhttp://tamillegends.com/sundara-pandiyan-tc-dvd/&lt;/a&gt;\n\n\nDownload More Movies At :                    &lt;a href=&quot; http://tamillegends.com/&quot; rel=&quot;nofollow&quot; target=&quot;_NEW&quot;&gt; http://tamillegends.com/&lt;/a&gt;","torrent":{"xt":"urn:btih:4312e2f2ae12f8ac133f811ace7d14bb16992628","amp;dn":"Sundara+Pandiyan+Tc+DvD+-+700Mb","amp;tr":["udp%3A%2F%2Ftracker.openbittorrent.com%3A80","udp%3A%2F%2Fopen.demonii.com%3A1337","udp%3A%2F%2Ftracker.coppersurfer.tk%3A6969","udp%3A%2F%2Fexodus.desync.com%3A6969"],"infoHash":"4312e2f2ae12f8ac133f811ace7d14bb16992628","infoHashBuffer":{"type":"Buffer","data":[67,18,226,242,174,18,248,172,19,63,129,26,206,125,20,187,22,153,38,40]},"announce":[],"urlList":[]}}