{"title":"QI.S10E08.Jumble.WS.PDTV.XviD-johncymru-via-AVIGUY.avi","uid":7786439,"size":367412088,"categoryP":"video","categoryS":"tv_shows","magnet":"?xt=urn:btih:43dadcbadbba00564961bf3bb00fbad510125fcb&amp;dn=QI.S10E08.Jumble.WS.PDTV.XviD-johncymru-via-AVIGUY.avi&amp;tr=udp%3A%2F%2Ftracker.openbittorrent.com%3A80&amp;tr=udp%3A%2F%2Fopen.demonii.com%3A1337&amp;tr=udp%3A%2F%2Ftracker.coppersurfer.tk%3A6969&amp;tr=udp%3A%2F%2Fexodus.desync.com%3A6969","seeders":0,"leechers":1,"uploader":"MP4SUX","files":1,"time":1351904360,"description":"This one's special - actual &quot;out of the Scene bubble&quot; native XVID AVI\nBrit show encoded by Brits and gratefully passed onto you by myself unchanged\nWell, tweaked the filename a bit - gotta keep track.\n\n========= IMDB.com/title/tt0380136/\n\nRelease Name: QI.S10E08.Jumble.WS.PDTV.XviD-johncymru-via-AVIGUY.avi\n\nFrom johncymru:\nRelease Date.: 2012-11-02\nRelease Size: 350 Mb\nPlay Time.......: 28:44\nResolution.....: 624x352\nVideo Codec...: XVID\nVideo Bitrate..: 1576 Kbps\nAudio: MP3 128 Kbps 48 KHz VBR\n","torrent":{"xt":"urn:btih:43dadcbadbba00564961bf3bb00fbad510125fcb","amp;dn":"QI.S10E08.Jumble.WS.PDTV.XviD-johncymru-via-AVIGUY.avi","amp;tr":["udp%3A%2F%2Ftracker.openbittorrent.com%3A80","udp%3A%2F%2Fopen.demonii.com%3A1337","udp%3A%2F%2Ftracker.coppersurfer.tk%3A6969","udp%3A%2F%2Fexodus.desync.com%3A6969"],"infoHash":"43dadcbadbba00564961bf3bb00fbad510125fcb","infoHashBuffer":{"type":"Buffer","data":[67,218,220,186,219,186,0,86,73,97,191,59,176,15,186,213,16,18,95,203]},"announce":[],"urlList":[]}}