{"title":"[MyTeenVideo.com] Mona","uid":6804928,"size":346858740,"categoryP":"porn","categoryS":"movies","magnet":"?xt=urn:btih:459b4eba8c68935800666ebd97aad556d924a663&amp;dn=%5BMyTeenVideo.com%5D+Mona&amp;tr=udp%3A%2F%2Ftracker.openbittorrent.com%3A80&amp;tr=udp%3A%2F%2Fopen.demonii.com%3A1337&amp;tr=udp%3A%2F%2Ftracker.coppersurfer.tk%3A6969&amp;tr=udp%3A%2F%2Fexodus.desync.com%3A6969","seeders":0,"leechers":1,"uploader":"chkm8te","files":4,"time":1320827035,"description":"Screens: &lt;a href=&quot;\nhttp://4ufrom.me/viewer.php?file=wt8dpch719o4mxktyqaa.jpg&quot; rel=&quot;nofollow&quot; target=&quot;_NEW&quot;&gt;\nhttp://4ufrom.me/viewer.php?file=wt8dpch719o4mxktyqaa.jpg&lt;/a&gt;\n &lt;a href=&quot;\nhttp://4ufrom.me/viewer.php?file=v28g3uqoqaxjhrg70hjy.jpg&quot; rel=&quot;nofollow&quot; target=&quot;_NEW&quot;&gt;\nhttp://4ufrom.me/viewer.php?file=v28g3uqoqaxjhrg70hjy.jpg&lt;/a&gt;","torrent":{"xt":"urn:btih:459b4eba8c68935800666ebd97aad556d924a663","amp;dn":"%5BMyTeenVideo.com%5D+Mona","amp;tr":["udp%3A%2F%2Ftracker.openbittorrent.com%3A80","udp%3A%2F%2Fopen.demonii.com%3A1337","udp%3A%2F%2Ftracker.coppersurfer.tk%3A6969","udp%3A%2F%2Fexodus.desync.com%3A6969"],"infoHash":"459b4eba8c68935800666ebd97aad556d924a663","infoHashBuffer":{"type":"Buffer","data":[69,155,78,186,140,104,147,88,0,102,110,189,151,170,213,86,217,36,166,99]},"announce":[],"urlList":[]}}