{"title":"Alaska the Last Frontier S02E02 HDTV x264-KILLERS[ettv]","uid":7712797,"size":508332771,"categoryP":"video","categoryS":"tv_shows","magnet":"?xt=urn:btih:49c1a7cf97d4b7e167092ab6d2ea5ac28cc63663&amp;dn=Alaska+the+Last+Frontier+S02E02+HDTV+x264-KILLERS%5Bettv%5D&amp;tr=udp%3A%2F%2Ftracker.openbittorrent.com%3A80&amp;tr=udp%3A%2F%2Fopen.demonii.com%3A1337&amp;tr=udp%3A%2F%2Ftracker.coppersurfer.tk%3A6969&amp;tr=udp%3A%2F%2Fexodus.desync.com%3A6969","seeders":0,"leechers":1,"uploader":"ettv","files":2,"time":1349848525,"description":"Rls: Alaska.the.Last.Frontier.S02E02.HDTV.x264-KILLERS\nDate: 10/09/2012\nChannel: Discovery\nCategory: Reality\n","torrent":{"xt":"urn:btih:49c1a7cf97d4b7e167092ab6d2ea5ac28cc63663","amp;dn":"Alaska+the+Last+Frontier+S02E02+HDTV+x264-KILLERS%5Bettv%5D","amp;tr":["udp%3A%2F%2Ftracker.openbittorrent.com%3A80","udp%3A%2F%2Fopen.demonii.com%3A1337","udp%3A%2F%2Ftracker.coppersurfer.tk%3A6969","udp%3A%2F%2Fexodus.desync.com%3A6969"],"infoHash":"49c1a7cf97d4b7e167092ab6d2ea5ac28cc63663","infoHashBuffer":{"type":"Buffer","data":[73,193,167,207,151,212,183,225,103,9,42,182,210,234,90,194,140,198,54,99]},"announce":[],"urlList":[]}}