{"title":"Adriana Lima Wallpapers 1600x1200 [Part VII]","uid":6824328,"size":4925965,"categoryP":"other","categoryS":"pictures","magnet":"?xt=urn:btih:527323cec9227f66eb12558bba712acac80b7309&amp;dn=Adriana+Lima+Wallpapers+1600x1200+%5BPart+VII%5D&amp;tr=udp%3A%2F%2Ftracker.openbittorrent.com%3A80&amp;tr=udp%3A%2F%2Fopen.demonii.com%3A1337&amp;tr=udp%3A%2F%2Ftracker.coppersurfer.tk%3A6969&amp;tr=udp%3A%2F%2Fexodus.desync.com%3A6969","seeders":0,"leechers":1,"uploader":"MrTPB","files":2,"time":1321518214,"description":"                   Adriana Lima Wallpapers 1600x1200 [Part VII]\n                 ________________________________________________\n\nSamples:-\n &lt;a href=&quot;\nhttp://themediapulse.com/abc/?v=1sos.jpg&quot; rel=&quot;nofollow&quot; target=&quot;_NEW&quot;&gt;\nhttp://themediapulse.com/abc/?v=1sos.jpg&lt;/a&gt;\n &lt;a href=&quot;\nhttp://themediapulse.com/abc/?v=adrianfof.jpg&quot; rel=&quot;nofollow&quot; target=&quot;_NEW&quot;&gt;\nhttp://themediapulse.com/abc/?v=adrianfof.jpg&lt;/a&gt;\n &lt;a href=&quot;\nhttp://themediapulse.com/abc/?v=adrianpvp.jpg&quot; rel=&quot;nofollow&quot; target=&quot;_NEW&quot;&gt;\nhttp://themediapulse.com/abc/?v=adrianpvp.jpg&lt;/a&gt;\n &lt;a href=&quot;\nhttp://themediapulse.com/abc/?v=adriannun.jpg&quot; rel=&quot;nofollow&quot; target=&quot;_NEW&quot;&gt;\nhttp://themediapulse.com/abc/?v=adriannun.jpg&lt;/a&gt;\n &lt;a href=&quot;\nhttp://themediapulse.com/abc/?v=adrianmpm.jpg&quot; rel=&quot;nofollow&quot; target=&quot;_NEW&quot;&gt;\nhttp://themediapulse.com/abc/?v=adrianmpm.jpg&lt;/a&gt;\n\n\nCheck My Other Uploads here:-\n    &lt;a href=&quot;\nhttp://thepiratebay.se/user/MrTPB&quot; rel=&quot;nofollow&quot; target=&quot;_NEW&quot;&gt;\nhttp://thepiratebay.se/user/MrTPB&lt;/a&gt; \n\n\nIMPORTANT !\nIf anyone need to send me a reseed request leave a comment on one of my recently uploaded torrents (And Please include the link to my torrent that you want me to reseed not the name) and Don't forget to add (+1) If you like this torrent :)\n\n\n                                                         \n \n                             One person seeds = Okay.\n                             Most people seed = Better.\n                             Everyone seeds   = Best.\n\n                 :::It is an honor to share with other people:::\n","torrent":{"xt":"urn:btih:527323cec9227f66eb12558bba712acac80b7309","amp;dn":"Adriana+Lima+Wallpapers+1600x1200+%5BPart+VII%5D","amp;tr":["udp%3A%2F%2Ftracker.openbittorrent.com%3A80","udp%3A%2F%2Fopen.demonii.com%3A1337","udp%3A%2F%2Ftracker.coppersurfer.tk%3A6969","udp%3A%2F%2Fexodus.desync.com%3A6969"],"infoHash":"527323cec9227f66eb12558bba712acac80b7309","infoHashBuffer":{"type":"Buffer","data":[82,115,35,206,201,34,127,102,235,18,85,139,186,113,42,202,200,11,115,9]},"announce":[],"urlList":[]}}