{"title":"Devin Townsend Project - By A Thread - KI DVD","uid":7721143,"size":6916322728,"categoryP":"video","categoryS":"movies","magnet":"?xt=urn:btih:54aa992832a644c57f760e86ed105ede3c885a9e&amp;dn=Devin+Townsend+Project+-+By+A+Thread+-+KI+DVD&amp;tr=udp%3A%2F%2Ftracker.openbittorrent.com%3A80&amp;tr=udp%3A%2F%2Fopen.demonii.com%3A1337&amp;tr=udp%3A%2F%2Ftracker.coppersurfer.tk%3A6969&amp;tr=udp%3A%2F%2Fexodus.desync.com%3A6969","seeders":0,"leechers":1,"uploader":"Kaligula6","files":1,"time":1350069335,"description":"Devin Townsend Project - By A Thread - KI DVD\n\n\nNovember 2011 the DEVIN TOWNSEND PROJECT\nplayed four epic sold out shows in London, England. By\nA Thread - Live In London 2011 contains all four sold-out\nUK shows where Ki, Addicted, Ghost, and\nDeconstruction were performed in their entirety live. By A\nThread... contains all four shows captured on four DVDs,\nplus a 5-CD set containing all the full live sets plus a\nbonus CD compiling all of the encores from all four\nevenings onto one disc.\n\n\n\nI support Devin Townsend, but this sold out fast, and I couldn't find it anywhere. I've seen it on ebay very expensive and fuck that.","torrent":{"xt":"urn:btih:54aa992832a644c57f760e86ed105ede3c885a9e","amp;dn":"Devin+Townsend+Project+-+By+A+Thread+-+KI+DVD","amp;tr":["udp%3A%2F%2Ftracker.openbittorrent.com%3A80","udp%3A%2F%2Fopen.demonii.com%3A1337","udp%3A%2F%2Ftracker.coppersurfer.tk%3A6969","udp%3A%2F%2Fexodus.desync.com%3A6969"],"infoHash":"54aa992832a644c57f760e86ed105ede3c885a9e","infoHashBuffer":{"type":"Buffer","data":[84,170,153,40,50,166,68,197,127,118,14,134,237,16,94,222,60,136,90,158]},"announce":[],"urlList":[]}}