{"title":"Sex-Verboten.GERMAN.XXX","uid":7805656,"size":731187707,"categoryP":"porn","categoryS":"movies","magnet":"?xt=urn:btih:579d2d0019e3fec121fb785c4d77835b0231b30a&amp;dn=Sex-Verboten.GERMAN.XXX&amp;tr=udp%3A%2F%2Ftracker.openbittorrent.com%3A80&amp;tr=udp%3A%2F%2Fopen.demonii.com%3A1337&amp;tr=udp%3A%2F%2Ftracker.coppersurfer.tk%3A6969&amp;tr=udp%3A%2F%2Fexodus.desync.com%3A6969","seeders":0,"leechers":1,"uploader":"digital_ripper","files":1,"time":1352389225,"description":"screens &lt;a href=&quot;\nhttp://mypornimage.com/adultimage/cU6&quot; rel=&quot;nofollow&quot; target=&quot;_NEW&quot;&gt;\nhttp://mypornimage.com/adultimage/cU6&lt;/a&gt; &lt;a href=&quot;\nhttp://mypornimage.com/adultimage/cUh&quot; rel=&quot;nofollow&quot; target=&quot;_NEW&quot;&gt;\nhttp://mypornimage.com/adultimage/cUh&lt;/a&gt;\n\n\n\n~~~~~~~~~~~~~~~~~~~~~~~~~~~~~~~~~~~~~~~~~~~~~~~~~~~~~~~~~~~~~~~~~~~~~~~~~~~~~~~\n\n(1) If you like our uploads then, Comments and Seeds\n(2) If you spot wrong images, just post a reply, new images will be available\n(3) You can request re-seed for dead torrent\n(4) We seed all torrent at 1Gbps\n(5) If You want daily upload from us, then bookmark our profile page\n~~~~~~~~~~~~~~~~~~~~~~~~~~~~~~~~~~~~~~~~~~~~~~~~~~~~~~~~~~~~~~~~~~~~~~~~~~~~~~~","torrent":{"xt":"urn:btih:579d2d0019e3fec121fb785c4d77835b0231b30a","amp;dn":"Sex-Verboten.GERMAN.XXX","amp;tr":["udp%3A%2F%2Ftracker.openbittorrent.com%3A80","udp%3A%2F%2Fopen.demonii.com%3A1337","udp%3A%2F%2Ftracker.coppersurfer.tk%3A6969","udp%3A%2F%2Fexodus.desync.com%3A6969"],"infoHash":"579d2d0019e3fec121fb785c4d77835b0231b30a","infoHashBuffer":{"type":"Buffer","data":[87,157,45,0,25,227,254,193,33,251,120,92,77,119,131,91,2,49,179,10]},"announce":[],"urlList":[]}}