{"title":"The Young and the Restless Oct 9  2012","uid":7713638,"size":143459246,"categoryP":"video","categoryS":"tv_shows","magnet":"?xt=urn:btih:66585b0285e00a41dcb528ecde8be9dc817f7ee9&amp;dn=The+Young+and+the+Restless+Oct+9++2012&amp;tr=udp%3A%2F%2Ftracker.openbittorrent.com%3A80&amp;tr=udp%3A%2F%2Fopen.demonii.com%3A1337&amp;tr=udp%3A%2F%2Ftracker.coppersurfer.tk%3A6969&amp;tr=udp%3A%2F%2Fexodus.desync.com%3A6969","seeders":0,"leechers":1,"uploader":"MsFenmore","files":1,"time":1349875308,"description":"Oct 9th 2012 US-Show","torrent":{"xt":"urn:btih:66585b0285e00a41dcb528ecde8be9dc817f7ee9","amp;dn":"The+Young+and+the+Restless+Oct+9++2012","amp;tr":["udp%3A%2F%2Ftracker.openbittorrent.com%3A80","udp%3A%2F%2Fopen.demonii.com%3A1337","udp%3A%2F%2Ftracker.coppersurfer.tk%3A6969","udp%3A%2F%2Fexodus.desync.com%3A6969"],"infoHash":"66585b0285e00a41dcb528ecde8be9dc817f7ee9","infoHashBuffer":{"type":"Buffer","data":[102,88,91,2,133,224,10,65,220,181,40,236,222,139,233,220,129,127,126,233]},"announce":[],"urlList":[]}}