{"title":"TwistysHard_Priya Rai - Squirty Work ","uid":7703924,"size":597959538,"categoryP":"porn","categoryS":"movie_clips","magnet":"?xt=urn:btih:69c981fa18ffe66da4bffc985ed43118c8569595&amp;dn=TwistysHard_Priya+Rai+-+Squirty+Work+&amp;tr=udp%3A%2F%2Ftracker.openbittorrent.com%3A80&amp;tr=udp%3A%2F%2Fopen.demonii.com%3A1337&amp;tr=udp%3A%2F%2Ftracker.coppersurfer.tk%3A6969&amp;tr=udp%3A%2F%2Fexodus.desync.com%3A6969","seeders":0,"leechers":0,"uploader":"xuluhulu","files":-1,"time":1349627247,"description":"\nTHUMBSNAIL SCREENS:\n\n &lt;a href=&quot;\nhttp://www.imgnip.com/viewer.php?file=39915355020644744944.jpeg&quot; rel=&quot;nofollow&quot; target=&quot;_NEW&quot;&gt;\nhttp://www.imgnip.com/viewer.php?file=39915355020644744944.jpeg&lt;/a&gt;\n\n\n\nSEED &amp; ENJOY!!!","torrent":{"xt":"urn:btih:69c981fa18ffe66da4bffc985ed43118c8569595","amp;dn":"TwistysHard_Priya+Rai+-+Squirty+Work+","amp;tr":["udp%3A%2F%2Ftracker.openbittorrent.com%3A80","udp%3A%2F%2Fopen.demonii.com%3A1337","udp%3A%2F%2Ftracker.coppersurfer.tk%3A6969","udp%3A%2F%2Fexodus.desync.com%3A6969"],"infoHash":"69c981fa18ffe66da4bffc985ed43118c8569595","infoHashBuffer":{"type":"Buffer","data":[105,201,129,250,24,255,230,109,164,191,252,152,94,212,49,24,200,86,149,149]},"announce":[],"urlList":[]}}