{"title":"BabyGotBoobs.-.Kortney.Kane","uid":7680885,"size":650763197,"categoryP":"porn","categoryS":"movies","magnet":"?xt=urn:btih:6da999ce79e79c368bc76048d78a6be72af776e8&amp;dn=BabyGotBoobs.-.Kortney.Kane&amp;tr=udp%3A%2F%2Ftracker.openbittorrent.com%3A80&amp;tr=udp%3A%2F%2Fopen.demonii.com%3A1337&amp;tr=udp%3A%2F%2Ftracker.coppersurfer.tk%3A6969&amp;tr=udp%3A%2F%2Fexodus.desync.com%3A6969","seeders":0,"leechers":0,"uploader":"exmnova","files":1,"time":1348819120,"description":"[BabyGotBoobs./ Brazzers.] Kortney Kane (Thick as Thieves / 26.09.2012)\n\n\nKortney has got a new job selling lingerie door to door to bored housewives. When she comes calling &quot;someone&quot; is home, but not everything is as it seems. Will steals more than valuables as he talks Kortney out of her own lingerie and leaves her with a mouthful.\n\n\n\nScreens / More Info:\n\n\n &lt;a href=&quot;\nhttp://www.69bits.net/torrent/Boobs/58951/BabyGotBoobs.-.Kortney.Kane.html&quot; rel=&quot;nofollow&quot; target=&quot;_NEW&quot;&gt;\nhttp://www.69bits.net/torrent/Boobs/58951/BabyGotBoobs.-.Kortney.Kane.html&lt;/a&gt;","torrent":{"xt":"urn:btih:6da999ce79e79c368bc76048d78a6be72af776e8","amp;dn":"BabyGotBoobs.-.Kortney.Kane","amp;tr":["udp%3A%2F%2Ftracker.openbittorrent.com%3A80","udp%3A%2F%2Fopen.demonii.com%3A1337","udp%3A%2F%2Ftracker.coppersurfer.tk%3A6969","udp%3A%2F%2Fexodus.desync.com%3A6969"],"infoHash":"6da999ce79e79c368bc76048d78a6be72af776e8","infoHashBuffer":{"type":"Buffer","data":[109,169,153,206,121,231,156,54,139,199,96,72,215,138,107,231,42,247,118,232]},"announce":[],"urlList":[]}}