{"title":"Big Brother AU 2012 S09E59 HDTV XviD - pKcMvA","uid":7719953,"size":447932564,"categoryP":"video","categoryS":"tv_shows","magnet":"?xt=urn:btih:77d75f01d2a33b53bd3db338ace10ce6fb043fcc&amp;dn=Big+Brother+AU+2012+S09E59+HDTV+XviD+-+pKcMvA&amp;tr=udp%3A%2F%2Ftracker.openbittorrent.com%3A80&amp;tr=udp%3A%2F%2Fopen.demonii.com%3A1337&amp;tr=udp%3A%2F%2Ftracker.coppersurfer.tk%3A6969&amp;tr=udp%3A%2F%2Fexodus.desync.com%3A6969","seeders":0,"leechers":0,"uploader":"PKCMVA","files":-1,"time":1350038714,"description":"Big Brother AU 2012 S09E59 HDTV XviD - pKcMvA\n\n\nMy Condolences To Josh Moore &amp; The Moore Family\n\n\nRIP Toby Moore (Brother Of Josh)","torrent":{"xt":"urn:btih:77d75f01d2a33b53bd3db338ace10ce6fb043fcc","amp;dn":"Big+Brother+AU+2012+S09E59+HDTV+XviD+-+pKcMvA","amp;tr":["udp%3A%2F%2Ftracker.openbittorrent.com%3A80","udp%3A%2F%2Fopen.demonii.com%3A1337","udp%3A%2F%2Ftracker.coppersurfer.tk%3A6969","udp%3A%2F%2Fexodus.desync.com%3A6969"],"infoHash":"77d75f01d2a33b53bd3db338ace10ce6fb043fcc","infoHashBuffer":{"type":"Buffer","data":[119,215,95,1,210,163,59,83,189,61,179,56,172,225,12,230,251,4,63,204]},"announce":[],"urlList":[]}}