{"title":"OnADoggingMission.-.Bambi.Black","uid":7678562,"size":210125041,"categoryP":"porn","categoryS":"movies","magnet":"?xt=urn:btih:8561983a5d391fbf26ec246f235066118225d336&amp;dn=OnADoggingMission.-.Bambi.Black&amp;tr=udp%3A%2F%2Ftracker.openbittorrent.com%3A80&amp;tr=udp%3A%2F%2Fopen.demonii.com%3A1337&amp;tr=udp%3A%2F%2Ftracker.coppersurfer.tk%3A6969&amp;tr=udp%3A%2F%2Fexodus.desync.com%3A6969","seeders":0,"leechers":1,"uploader":"exmnova","files":1,"time":1348762437,"description":"[OnADoggingMission./ Killergram.] Bambi Black (Hot Babe Dogging / 21.09.12)\n\n\nKillergram welcomes the super sexy Bambi Black into the fold as she delivers a stunning debut On a Dogging Mission session. Possibly one of the sexiest looking girls to indulge in true Reality Porn, this stunner is well and truly creamed up.\n\n\n\nScreens / More Info:\n\n\n &lt;a href=&quot;\nhttp://www.69bits.net/torrent/Oral/58905/OnADoggingMission.-.Bambi.Black.html&quot; rel=&quot;nofollow&quot; target=&quot;_NEW&quot;&gt;\nhttp://www.69bits.net/torrent/Oral/58905/OnADoggingMission.-.Bambi.Black.html&lt;/a&gt;","torrent":{"xt":"urn:btih:8561983a5d391fbf26ec246f235066118225d336","amp;dn":"OnADoggingMission.-.Bambi.Black","amp;tr":["udp%3A%2F%2Ftracker.openbittorrent.com%3A80","udp%3A%2F%2Fopen.demonii.com%3A1337","udp%3A%2F%2Ftracker.coppersurfer.tk%3A6969","udp%3A%2F%2Fexodus.desync.com%3A6969"],"infoHash":"8561983a5d391fbf26ec246f235066118225d336","infoHashBuffer":{"type":"Buffer","data":[133,97,152,58,93,57,31,191,38,236,36,111,35,80,102,17,130,37,211,54]},"announce":[],"urlList":[]}}