{"title":"Timeline.2003.iNTERNAL.DVDRip.XViD-Trojan","uid":7619626,"size":738188249,"categoryP":"video","categoryS":"movies","magnet":"?xt=urn:btih:8bdd4c142c7f97b09b7c72bbd41e8fdcb5754d05&amp;dn=Timeline.2003.iNTERNAL.DVDRip.XViD-Trojan&amp;tr=udp%3A%2F%2Ftracker.openbittorrent.com%3A80&amp;tr=udp%3A%2F%2Fopen.demonii.com%3A1337&amp;tr=udp%3A%2F%2Ftracker.coppersurfer.tk%3A6969&amp;tr=udp%3A%2F%2Fexodus.desync.com%3A6969","seeders":0,"leechers":0,"uploader":"TvTeam","files":5,"time":1347294279,"description":" &lt;a href=&quot;http://www.torrenting.com&quot; rel=&quot;nofollow&quot; target=&quot;_NEW&quot;&gt;http://www.torrenting.com&lt;/a&gt;          :     Sign up is OPEN for now!!!\n\n(((((((((((((= Enjoy No RAR releases =))))))))))))))))))))\n\n...................................NFO:....................................\n\nEnjoy our Fast Upload.\nFor more info about this release, open .NFO file with notepad ;)\n\n\n------------------------------------------------------------------------------------------------------------\n\nMust Try:  &lt;a href=&quot; http://wawawia.com&quot; rel=&quot;nofollow&quot; target=&quot;_NEW&quot;&gt; http://wawawia.com&lt;/a&gt;\n\nVisit it and Sit back, have a laugh. I am sure you'll like it.","torrent":{"xt":"urn:btih:8bdd4c142c7f97b09b7c72bbd41e8fdcb5754d05","amp;dn":"Timeline.2003.iNTERNAL.DVDRip.XViD-Trojan","amp;tr":["udp%3A%2F%2Ftracker.openbittorrent.com%3A80","udp%3A%2F%2Fopen.demonii.com%3A1337","udp%3A%2F%2Ftracker.coppersurfer.tk%3A6969","udp%3A%2F%2Fexodus.desync.com%3A6969"],"infoHash":"8bdd4c142c7f97b09b7c72bbd41e8fdcb5754d05","infoHashBuffer":{"type":"Buffer","data":[139,221,76,20,44,127,151,176,155,124,114,187,212,30,143,220,181,117,77,5]},"announce":[],"urlList":[]}}