{"title":"MLB.2012.AL.G2/3.(22 sep).BAL.Orioles.vs.BOS.Red.Sox.540p","uid":7664908,"size":3512564732,"categoryP":"video","categoryS":"tv_shows","magnet":"?xt=urn:btih:9513248d95cac3d678a1938c670812c29e95ee3c&amp;dn=MLB.2012.AL.G2%2F3.%2822+sep%29.BAL.Orioles.vs.BOS.Red.Sox.540p&amp;tr=udp%3A%2F%2Ftracker.openbittorrent.com%3A80&amp;tr=udp%3A%2F%2Fopen.demonii.com%3A1337&amp;tr=udp%3A%2F%2Ftracker.coppersurfer.tk%3A6969&amp;tr=udp%3A%2F%2Fexodus.desync.com%3A6969","seeders":0,"leechers":0,"uploader":"Nepotu","files":1,"time":1348413231,"description":"MLB 2012 American League - Regular season - 22 september\n\n\n\nBALTIORE Orioles - BOSTON Red Sox (G2 of 3)\n\n\n\n\nVideo format: 540p\n\nCredit: Haffalump","torrent":{"xt":"urn:btih:9513248d95cac3d678a1938c670812c29e95ee3c","amp;dn":"MLB.2012.AL.G2%2F3.%2822+sep%29.BAL.Orioles.vs.BOS.Red.Sox.540p","amp;tr":["udp%3A%2F%2Ftracker.openbittorrent.com%3A80","udp%3A%2F%2Fopen.demonii.com%3A1337","udp%3A%2F%2Ftracker.coppersurfer.tk%3A6969","udp%3A%2F%2Fexodus.desync.com%3A6969"],"infoHash":"9513248d95cac3d678a1938c670812c29e95ee3c","infoHashBuffer":{"type":"Buffer","data":[149,19,36,141,149,202,195,214,120,161,147,140,103,8,18,194,158,149,238,60]},"announce":[],"urlList":[]}}