{"title":"wb-df6","uid":7728149,"size":2929585406,"categoryP":"porn","categoryS":"movies","magnet":"?xt=urn:btih:9afd2ea93b835b47a25521e3e109856d8eab9574&amp;dn=wb-df6&amp;tr=udp%3A%2F%2Ftracker.openbittorrent.com%3A80&amp;tr=udp%3A%2F%2Fopen.demonii.com%3A1337&amp;tr=udp%3A%2F%2Ftracker.coppersurfer.tk%3A6969&amp;tr=udp%3A%2F%2Fexodus.desync.com%3A6969","seeders":0,"leechers":1,"uploader":"shae2005","files":2,"time":1350273554,"description":"WB-DF6\nDouble Feature\nWB-DF6-1\nAngelina Love, Brooke, Lea Magic, \nLuscious Eden, Winnie\n~~~~~~~~~~~~~~~~~~~~~~~~~~~~~~~~~~~~\nAVI\n1:59:12\n624x352\n1.36gbs\nPreview &lt;a href=&quot;\nhttp://www.cweb-pix.com/wfy&quot; rel=&quot;nofollow&quot; target=&quot;_NEW&quot;&gt;\nhttp://www.cweb-pix.com/wfy&lt;/a&gt;\n~~~~~~~~~~~~~~~\nWB-DF6-2\nDale DaBone, Lily Carter, \nJessie Andrews, Richie Deville\nAVI\n1:55:10\n624x352\n1.36gbs\nPreview &lt;a href=&quot;\nhttp://www.cweb-pix.com/wfM&quot; rel=&quot;nofollow&quot; target=&quot;_NEW&quot;&gt;\nhttp://www.cweb-pix.com/wfM&lt;/a&gt;","torrent":{"xt":"urn:btih:9afd2ea93b835b47a25521e3e109856d8eab9574","amp;dn":"wb-df6","amp;tr":["udp%3A%2F%2Ftracker.openbittorrent.com%3A80","udp%3A%2F%2Fopen.demonii.com%3A1337","udp%3A%2F%2Ftracker.coppersurfer.tk%3A6969","udp%3A%2F%2Fexodus.desync.com%3A6969"],"infoHash":"9afd2ea93b835b47a25521e3e109856d8eab9574","infoHashBuffer":{"type":"Buffer","data":[154,253,46,169,59,131,91,71,162,85,33,227,225,9,133,109,142,171,149,116]},"announce":[],"urlList":[]}}