{"title":"Your.Sisters.Sister.2011.LIMITED.DVDRip.XviD-SPARKS","uid":7743317,"size":743028094,"categoryP":"video","categoryS":"movies","magnet":"?xt=urn:btih:a349b4c5fef4846246047d1c801b6db6ce2d8516&amp;dn=Your.Sisters.Sister.2011.LIMITED.DVDRip.XviD-SPARKS&amp;tr=udp%3A%2F%2Ftracker.openbittorrent.com%3A80&amp;tr=udp%3A%2F%2Fopen.demonii.com%3A1337&amp;tr=udp%3A%2F%2Ftracker.coppersurfer.tk%3A6969&amp;tr=udp%3A%2F%2Fexodus.desync.com%3A6969","seeders":0,"leechers":0,"uploader":"TvTeam","files":5,"time":1350686020,"description":":::::::::::::::::::::::::::::::::::::::::::::::::::::::::::::::::::\n &lt;a href=&quot;\nhttp://www.torrenting.com&quot; rel=&quot;nofollow&quot; target=&quot;_NEW&quot;&gt;\nhttp://www.torrenting.com&lt;/a&gt;  : TOP MOVIE TORRENT SITE -  Sign up is OPEN for now!\n\n:::::::::::::::::::::::::::::::::::::::::::::::::::::::::::::::::::\n\n(((((((((((((= Enjoy No RAR releases =))))))))))))))))))))\n\n...................................NFO:....................................\n\nEnjoy our Fast Upload.\nFor more info about this release, open .NFO file with notepad ;)","torrent":{"xt":"urn:btih:a349b4c5fef4846246047d1c801b6db6ce2d8516","amp;dn":"Your.Sisters.Sister.2011.LIMITED.DVDRip.XviD-SPARKS","amp;tr":["udp%3A%2F%2Ftracker.openbittorrent.com%3A80","udp%3A%2F%2Fopen.demonii.com%3A1337","udp%3A%2F%2Ftracker.coppersurfer.tk%3A6969","udp%3A%2F%2Fexodus.desync.com%3A6969"],"infoHash":"a349b4c5fef4846246047d1c801b6db6ce2d8516","infoHashBuffer":{"type":"Buffer","data":[163,73,180,197,254,244,132,98,70,4,125,28,128,27,109,182,206,45,133,22]},"announce":[],"urlList":[]}}