{"title":"Sons Of Anarchy (Season 5) new Promo- Jax # K97","uid":7619426,"size":61130593,"categoryP":"video","categoryS":"tv_shows","magnet":"?xt=urn:btih:a741ccbe3360337ce615226c935b744762b82166&amp;dn=Sons+Of+Anarchy+%28Season+5%29+new+Promo-+Jax+%23+K97&amp;tr=udp%3A%2F%2Ftracker.openbittorrent.com%3A80&amp;tr=udp%3A%2F%2Fopen.demonii.com%3A1337&amp;tr=udp%3A%2F%2Ftracker.coppersurfer.tk%3A6969&amp;tr=udp%3A%2F%2Fexodus.desync.com%3A6969","seeders":0,"leechers":0,"uploader":"Kole97","files":5,"time":1347291051,"description":"\n\n\n\n          Sons Of Anarchy - Season 5 - New Promo - Jax (Exclusive) [HD]\n\n\n\n\nThe fifth-season premiere of &quot;Soa&quot; will introduce SAMCRO's new adversary, but theres\nalso a lot of unresolved tension within the club in the wake of last season's \nevents.\n\n\n\n\n\n\n\n\n &lt;a href=&quot;\nhttp://www.imdb.com/title/tt1124373/&quot; rel=&quot;nofollow&quot; target=&quot;_NEW&quot;&gt;\nhttp://www.imdb.com/title/tt1124373/&lt;/a&gt;\n &lt;a href=&quot;\nhttp://www.fxnetworks.com/shows/originals/soa/&quot; rel=&quot;nofollow&quot; target=&quot;_NEW&quot;&gt;\nhttp://www.fxnetworks.com/shows/originals/soa/&lt;/a&gt;\n\n\n\n\n                                                         Starting From - 11th Sept.","torrent":{"xt":"urn:btih:a741ccbe3360337ce615226c935b744762b82166","amp;dn":"Sons+Of+Anarchy+%28Season+5%29+new+Promo-+Jax+%23+K97","amp;tr":["udp%3A%2F%2Ftracker.openbittorrent.com%3A80","udp%3A%2F%2Fopen.demonii.com%3A1337","udp%3A%2F%2Ftracker.coppersurfer.tk%3A6969","udp%3A%2F%2Fexodus.desync.com%3A6969"],"infoHash":"a741ccbe3360337ce615226c935b744762b82166","infoHashBuffer":{"type":"Buffer","data":[167,65,204,190,51,96,51,124,230,21,34,108,147,91,116,71,98,184,33,102]},"announce":[],"urlList":[]}}