{"title":"True Bloodthirst (2012) HDTVRIP XVID 1.5 GB DD 5.1 NL Subs TBS","uid":7662299,"size":1563816002,"categoryP":"video","categoryS":"hd___tv_shows","magnet":"?xt=urn:btih:bcbd20cee473c20039d505699fa70e9376294d5c&amp;dn=True+Bloodthirst+%282012%29+HDTVRIP+XVID+1.5+GB+DD+5.1+NL+Subs+TBS&amp;tr=udp%3A%2F%2Ftracker.openbittorrent.com%3A80&amp;tr=udp%3A%2F%2Fopen.demonii.com%3A1337&amp;tr=udp%3A%2F%2Ftracker.coppersurfer.tk%3A6969&amp;tr=udp%3A%2F%2Fexodus.desync.com%3A6969","seeders":0,"leechers":0,"uploader":"Betty-Boop","files":-1,"time":1348343542,"description":"True Bloodthirst (2012) HDTVRIP XVID 1.5 GB DD 5.1 NL Subs TBS\n\n\nVerenigde Staten\nSciencefiction / Horror\n\ngeregisseerd door Todor Chapkanov\nmet Andrew Lee Potts, Neil Jackson en Roark Critchlow\n\nPlaats van handeling is Boekarest, in een niet al te verre toekomst. De mensenpopulatie is slinkende, daarentegen neemt het aantal vampiers explosief toe. Opgestaan uit de schaduwen van een decennium eerder, bewegen de vampiers zich nu openlijk onder de menselijke bevolking. Er heerst een onzekere staat van vrede tussen de beide groepen. Die is te danken aan de introductie van een synthetische bloedvervanger, ter beschikking gesteld door de Roemeense overheid. Vampiers hoeven daarom niet langer jacht op mensen te maken, om zich met hun bloed te voeden, zoals vroeger gebruikelijk was. Maar desondanks is het een vredesbestand waarmee niet iedereen even gelukkig is.\n\n\nEnglish\n\nSet in a not-too-distant future in which a synthetic blood substitute, dispensed by the Romanian government, allows humans and vampires to potentially co-exist. \n\n\n\n\n\n\nMovie..............: True Bloodthirst (2012)\nGenre..............: Sciencefiction / Horror\nSource.............: True.Bloodthirst.2012.720p.HDTV.x264-PTMiR [PublicHD]\nRuntime............: 85 minuten.\nSubtitles.NL.......: Vertaald door JR Jansen, Jolly en Depositair, Heel goed Teamwork Klasse job *****\nControle...........: Depositair\nBewerking+Resync...: Depositair\n\nMet dank aan DE kanjers van vertalers\n\nSIZE............: 1495 MB\nFORM............: AVI\nVIDEO CODEC.....: XVID\nBREEDTE.........: 720\nHOOGTE..........: 416\nAUDIO...........: Engels\nAUDIO CODE......: AC3\nBITRATE.........: 384\nCHANNELS........: 5\nSUBTITELS.......: NL ingebakken\nGenre...........: Horror, Science Fiction\nGrootte  \t:   1.54 GB\n &lt;a href=&quot;\nhttp://www.moviemeter.nl/film/78807&quot; rel=&quot;nofollow&quot; target=&quot;_NEW&quot;&gt;\nhttp://www.moviemeter.nl/film/78807&lt;/a&gt; &lt;a href=&quot;\nhttp://www.imdb.com/title/tt1982882&quot; rel=&quot;nofollow&quot; target=&quot;_NEW&quot;&gt;\nhttp://www.imdb.com/title/tt1982882&lt;/a&gt;\n\n\nscreens : http://lookpic.com/O/i2/627/2hlLaR6U.jpeg\n\n\n@@@@@@@@@@@@@@@@@@@@@@@@@@@@@@@\n\nKom ook eens kijken :\n &lt;a href=&quot;\nhttp://black-sam.org&quot; rel=&quot;nofollow&quot; target=&quot;_NEW&quot;&gt;\nhttp://black-sam.org&lt;/a&gt;\n\n\nEnjoy\n\n\n@@@@@@@@@@@@@@@@@@@@@@@@@@@@@@","torrent":{"xt":"urn:btih:bcbd20cee473c20039d505699fa70e9376294d5c","amp;dn":"True+Bloodthirst+%282012%29+HDTVRIP+XVID+1.5+GB+DD+5.1+NL+Subs+TBS","amp;tr":["udp%3A%2F%2Ftracker.openbittorrent.com%3A80","udp%3A%2F%2Fopen.demonii.com%3A1337","udp%3A%2F%2Ftracker.coppersurfer.tk%3A6969","udp%3A%2F%2Fexodus.desync.com%3A6969"],"infoHash":"bcbd20cee473c20039d505699fa70e9376294d5c","infoHashBuffer":{"type":"Buffer","data":[188,189,32,206,228,115,194,0,57,213,5,105,159,167,14,147,118,41,77,92]},"announce":[],"urlList":[]}}