{"title":"[IKnowThatGirl] Whitney Westgate (Horny Everywhere / 03/10/2012)","uid":7694674,"size":542919111,"categoryP":"porn","categoryS":"movies","magnet":"?xt=urn:btih:be80cdc8876bf5869a537ae7cce9147394742362&amp;dn=%5BIKnowThatGirl%5D+Whitney+Westgate+%28Horny+Everywhere+%2F+03%2F10%2F2012%29&amp;tr=udp%3A%2F%2Ftracker.openbittorrent.com%3A80&amp;tr=udp%3A%2F%2Fopen.demonii.com%3A1337&amp;tr=udp%3A%2F%2Ftracker.coppersurfer.tk%3A6969&amp;tr=udp%3A%2F%2Fexodus.desync.com%3A6969","seeders":0,"leechers":1,"uploader":"chkm8te","files":1,"time":1349321222,"description":"[IKnowThatGirl] Whitney Westgate (Horny Everywhere / 03/10/2012)\n\nWhitney is Always Horny, That's why I Always bring a camera with me. And she gets out of control when I film her sucking my cock.\n\nScreens: &lt;a href=&quot;\nhttp://xxxhost.me/viewer.php?file=6uwox6mkk71zyiw6ttbv.jpg&quot; rel=&quot;nofollow&quot; target=&quot;_NEW&quot;&gt;\nhttp://xxxhost.me/viewer.php?file=6uwox6mkk71zyiw6ttbv.jpg&lt;/a&gt;\n &lt;a href=&quot;\nhttp://xxxhost.me/viewer.php?file=1539w1zqqsk5t54w4ydc.jpg&quot; rel=&quot;nofollow&quot; target=&quot;_NEW&quot;&gt;\nhttp://xxxhost.me/viewer.php?file=1539w1zqqsk5t54w4ydc.jpg&lt;/a&gt;","torrent":{"xt":"urn:btih:be80cdc8876bf5869a537ae7cce9147394742362","amp;dn":"%5BIKnowThatGirl%5D+Whitney+Westgate+%28Horny+Everywhere+%2F+03%2F10%2F2012%29","amp;tr":["udp%3A%2F%2Ftracker.openbittorrent.com%3A80","udp%3A%2F%2Fopen.demonii.com%3A1337","udp%3A%2F%2Ftracker.coppersurfer.tk%3A6969","udp%3A%2F%2Fexodus.desync.com%3A6969"],"infoHash":"be80cdc8876bf5869a537ae7cce9147394742362","infoHashBuffer":{"type":"Buffer","data":[190,128,205,200,135,107,245,134,154,83,122,231,204,233,20,115,148,116,35,98]},"announce":[],"urlList":[]}}