{"title":"3 Day Rule - Alyssa Branch.mp4","uid":7777586,"size":247066328,"categoryP":"porn","categoryS":"movie_clips","magnet":"?xt=urn:btih:bf7ff1dffa3dacb149c15d9bc138fb7ef499395e&amp;dn=3+Day+Rule+-+Alyssa+Branch.mp4&amp;tr=udp%3A%2F%2Ftracker.openbittorrent.com%3A80&amp;tr=udp%3A%2F%2Fopen.demonii.com%3A1337&amp;tr=udp%3A%2F%2Ftracker.coppersurfer.tk%3A6969&amp;tr=udp%3A%2F%2Fexodus.desync.com%3A6969","seeders":0,"leechers":1,"uploader":"Pornmaze","files":1,"time":1351695102,"description":"3 Day Rule - Alyssa Branch.mp4\n\n2012, Gonzo, Young, Hardcore, Oral, XXX, Adult\n\n720 x 400\n\n00:22:24\n\n235.62 MB\n\nScreens\n\n\n","torrent":{"xt":"urn:btih:bf7ff1dffa3dacb149c15d9bc138fb7ef499395e","amp;dn":"3+Day+Rule+-+Alyssa+Branch.mp4","amp;tr":["udp%3A%2F%2Ftracker.openbittorrent.com%3A80","udp%3A%2F%2Fopen.demonii.com%3A1337","udp%3A%2F%2Ftracker.coppersurfer.tk%3A6969","udp%3A%2F%2Fexodus.desync.com%3A6969"],"infoHash":"bf7ff1dffa3dacb149c15d9bc138fb7ef499395e","infoHashBuffer":{"type":"Buffer","data":[191,127,241,223,250,61,172,177,73,193,93,155,193,56,251,126,244,153,57,94]},"announce":[],"urlList":[]}}