{"title":"Resident Evil (2002)-DVDRIp Xvid-THC","uid":7684246,"size":1505465554,"categoryP":"video","categoryS":"movies","magnet":"?xt=urn:btih:d4b8ba16928213cf2ac6e8e9e4ebcdc599c72e96&amp;dn=Resident+Evil+%282002%29-DVDRIp+Xvid-THC&amp;tr=udp%3A%2F%2Ftracker.openbittorrent.com%3A80&amp;tr=udp%3A%2F%2Fopen.demonii.com%3A1337&amp;tr=udp%3A%2F%2Ftracker.coppersurfer.tk%3A6969&amp;tr=udp%3A%2F%2Fexodus.desync.com%3A6969","seeders":0,"leechers":1,"uploader":"TvTeam","files":5,"time":1348903143,"description":" &lt;a href=&quot;http://www.torrenting.com&quot; rel=&quot;nofollow&quot; target=&quot;_NEW&quot;&gt;http://www.torrenting.com&lt;/a&gt;          :     Sign up is OPEN for now!!!\n\n(((((((((((((= Enjoy No RAR releases =))))))))))))))))))))\n\n...................................NFO:....................................\n\nEnjoy our Fast Upload.\nFor more info about this release, open .NFO file with notepad ;)\n\n\n------------------------------------------------------------------------------------------------------------\n\nMust Try:  \n\nVisit it and Sit back, have a laugh. I am sure you'll like it.","torrent":{"xt":"urn:btih:d4b8ba16928213cf2ac6e8e9e4ebcdc599c72e96","amp;dn":"Resident+Evil+%282002%29-DVDRIp+Xvid-THC","amp;tr":["udp%3A%2F%2Ftracker.openbittorrent.com%3A80","udp%3A%2F%2Fopen.demonii.com%3A1337","udp%3A%2F%2Ftracker.coppersurfer.tk%3A6969","udp%3A%2F%2Fexodus.desync.com%3A6969"],"infoHash":"d4b8ba16928213cf2ac6e8e9e4ebcdc599c72e96","infoHashBuffer":{"type":"Buffer","data":[212,184,186,22,146,130,19,207,42,198,232,233,228,235,205,197,153,199,46,150]},"announce":[],"urlList":[]}}