{"title":"Diario El mundo 26-9-2012","uid":7673920,"size":5820220,"categoryP":"other","categoryS":"e_books","magnet":"?xt=urn:btih:d7cf7d72df8338187259d43e6487569f24faf834&amp;dn=Diario+El+mundo+26-9-2012&amp;tr=udp%3A%2F%2Ftracker.openbittorrent.com%3A80&amp;tr=udp%3A%2F%2Fopen.demonii.com%3A1337&amp;tr=udp%3A%2F%2Ftracker.coppersurfer.tk%3A6969&amp;tr=udp%3A%2F%2Fexodus.desync.com%3A6969","seeders":0,"leechers":1,"uploader":"furtaperas","files":-1,"time":1348649600,"description":"el mundo ","torrent":{"xt":"urn:btih:d7cf7d72df8338187259d43e6487569f24faf834","amp;dn":"Diario+El+mundo+26-9-2012","amp;tr":["udp%3A%2F%2Ftracker.openbittorrent.com%3A80","udp%3A%2F%2Fopen.demonii.com%3A1337","udp%3A%2F%2Ftracker.coppersurfer.tk%3A6969","udp%3A%2F%2Fexodus.desync.com%3A6969"],"infoHash":"d7cf7d72df8338187259d43e6487569f24faf834","infoHashBuffer":{"type":"Buffer","data":[215,207,125,114,223,131,56,24,114,89,212,62,100,135,86,159,36,250,248,52]},"announce":[],"urlList":[]}}