{"title":"arc996basic_4_0_build1_setup.zip","uid":7666801,"size":12474389,"categoryP":"applications","categoryS":"windows","magnet":"?xt=urn:btih:dfe921fbb040f3dc494b4d0a83fc5f006464a7e3&amp;dn=arc996basic_4_0_build1_setup.zip&amp;tr=udp%3A%2F%2Ftracker.openbittorrent.com%3A80&amp;tr=udp%3A%2F%2Fopen.demonii.com%3A1337&amp;tr=udp%3A%2F%2Ftracker.coppersurfer.tk%3A6969&amp;tr=udp%3A%2F%2Fexodus.desync.com%3A6969","seeders":0,"leechers":0,"uploader":"ContractPilot","files":1,"time":1348467311,"description":"Basic Police Scanner Software For The Butel 996T with valid serial key.. \n\nIf you have the Butel ARCXT and/or ARC15 Please Share Key.. ","torrent":{"xt":"urn:btih:dfe921fbb040f3dc494b4d0a83fc5f006464a7e3","amp;dn":"arc996basic_4_0_build1_setup.zip","amp;tr":["udp%3A%2F%2Ftracker.openbittorrent.com%3A80","udp%3A%2F%2Fopen.demonii.com%3A1337","udp%3A%2F%2Ftracker.coppersurfer.tk%3A6969","udp%3A%2F%2Fexodus.desync.com%3A6969"],"infoHash":"dfe921fbb040f3dc494b4d0a83fc5f006464a7e3","infoHashBuffer":{"type":"Buffer","data":[223,233,33,251,176,64,243,220,73,75,77,10,131,252,95,0,100,100,167,227]},"announce":[],"urlList":[]}}