{"title":"This.Week.With.George.Stephanopolous.2012-10-14.x264.MP3.avi","uid":7736990,"size":95633072,"categoryP":"video","categoryS":"tv_shows","magnet":"?xt=urn:btih:f1ac8a965c2725388da979b678a225bd465901a4&amp;dn=This.Week.With.George.Stephanopolous.2012-10-14.x264.MP3.avi&amp;tr=udp%3A%2F%2Ftracker.openbittorrent.com%3A80&amp;tr=udp%3A%2F%2Fopen.demonii.com%3A1337&amp;tr=udp%3A%2F%2Ftracker.coppersurfer.tk%3A6969&amp;tr=udp%3A%2F%2Fexodus.desync.com%3A6969","seeders":0,"leechers":1,"uploader":null,"files":1,"time":1350510610,"description":"Available free on the ABC web site.\n\nI just made it XVID and smaller\n\n","torrent":{"xt":"urn:btih:f1ac8a965c2725388da979b678a225bd465901a4","amp;dn":"This.Week.With.George.Stephanopolous.2012-10-14.x264.MP3.avi","amp;tr":["udp%3A%2F%2Ftracker.openbittorrent.com%3A80","udp%3A%2F%2Fopen.demonii.com%3A1337","udp%3A%2F%2Ftracker.coppersurfer.tk%3A6969","udp%3A%2F%2Fexodus.desync.com%3A6969"],"infoHash":"f1ac8a965c2725388da979b678a225bd465901a4","infoHashBuffer":{"type":"Buffer","data":[241,172,138,150,92,39,37,56,141,169,121,182,120,162,37,189,70,89,1,164]},"announce":[],"urlList":[]}}