{"title":"LatinAdultery - Yurizan Beltran.wmv","uid":6822480,"size":506697017,"categoryP":"porn","categoryS":"movie_clips","magnet":"?xt=urn:btih:f20bff139bab96eb0b1984bb48f77db38fcd281b&amp;dn=LatinAdultery+-+Yurizan+Beltran.wmv&amp;tr=udp%3A%2F%2Ftracker.openbittorrent.com%3A80&amp;tr=udp%3A%2F%2Fopen.demonii.com%3A1337&amp;tr=udp%3A%2F%2Ftracker.coppersurfer.tk%3A6969&amp;tr=udp%3A%2F%2Fexodus.desync.com%3A6969","seeders":0,"leechers":1,"uploader":"1.No.1","files":1,"time":1321452509,"description":"LatinAdultery - Yurizan Beltran.wmv\n\nBig tits, Straight, Hardcore, Latina, XXX, Adult\n\n850 x 480\n\n00:32:01\n\n483.22 MB\n\nScreens\n &lt;a href=&quot;\nhttp://www.pixsor.com/share-4213_4EC3D6DF.html&quot; rel=&quot;nofollow&quot; target=&quot;_NEW&quot;&gt;\nhttp://www.pixsor.com/share-4213_4EC3D6DF.html&lt;/a&gt;\n &lt;a href=&quot;\nhttp://www.pixsor.com/share-2C84_4EC3D6DF.html&quot; rel=&quot;nofollow&quot; target=&quot;_NEW&quot;&gt;\nhttp://www.pixsor.com/share-2C84_4EC3D6DF.html&lt;/a&gt;","torrent":{"xt":"urn:btih:f20bff139bab96eb0b1984bb48f77db38fcd281b","amp;dn":"LatinAdultery+-+Yurizan+Beltran.wmv","amp;tr":["udp%3A%2F%2Ftracker.openbittorrent.com%3A80","udp%3A%2F%2Fopen.demonii.com%3A1337","udp%3A%2F%2Ftracker.coppersurfer.tk%3A6969","udp%3A%2F%2Fexodus.desync.com%3A6969"],"infoHash":"f20bff139bab96eb0b1984bb48f77db38fcd281b","infoHashBuffer":{"type":"Buffer","data":[242,11,255,19,155,171,150,235,11,25,132,187,72,247,125,179,143,205,40,27]},"announce":[],"urlList":[]}}